git_multi_clone/__init__.py
git_multi_clone/__main__.py
git_multi_clone/cli.py
git_multi_clone/multi_clone.py
git_multi_clone-0.1.1.dist-info/METADATA
git_multi_clone-0.1.1.dist-info/WHEEL
git_multi_clone-0.1.1.dist-info/entry_points.txt
git_multi_clone-0.1.1.dist-info/top_level.txt
git_multi_clone-0.1.1.dist-info/RECORD
