Metadata-Version: 2.1
Name: git-multi-clone
Version: 0.1.1
Summary: CLI tool to clone multiple git repositories
Author-email: Federico Oberndorfer <federico.ober@hotmail.com>
License: MIT License
Project-URL: Repository, https://github.com/federicober/git-multi-clone
Requires-Dist: typer >=0.4.0
Requires-Dist: GitPython >=3.1.0
Requires-Dist: pydantic >=2.0.0
Requires-Dist: toml >=0.10.2
Provides-Extra: dev
Requires-Dist: pytest >=6.0 ; extra == 'dev'
Requires-Dist: mypy >=0.910 ; extra == 'dev'
Requires-Dist: ruff >=0.0.262 ; extra == 'dev'
Requires-Dist: types-toml ; extra == 'dev'
